Metadata-Version: 2.1
Name: vaststring
Version: 0.1.0
Summary: A collection of advanced string manipulation functions for Python.
Home-page: https://github.com/your_username/vaststring
Author: Your Name
Author-email: your.email@example.com
License: MIT
Classifier: Programming Language :: Python :: 3
Classifier: License :: OSI Approved :: MIT License
Classifier: Operating System :: OS Independent
